bullet_train/__init__.py
bullet_train/bullet_train.py
bullet_train-1.0.5.dist-info/METADATA
bullet_train-1.0.5.dist-info/WHEEL
bullet_train-1.0.5.dist-info/top_level.txt
bullet_train-1.0.5.dist-info/RECORD
