Metadata-Version: 2.1
Name: bullet-train
Version: 1.0.5
Summary: Bullet Train Python SDK
Home-page: https://github.com/solidstategroup/bullet-train-python-client
Author: Solid State Group
Author-email: bullettrain@solidstategroup.com
License: BSD3
Keywords: feature,flag,bullet,train,remote,config
Platform: UNKNOWN
Classifier: License :: OSI Approved :: BSD License
Classifier: Programming Language :: Python :: 2
Classifier: Programming Language :: Python :: 2.6
Classifier: Programming Language :: Python :: 2.7
Classifier: Programming Language :: Python :: 3
Classifier: Programming Language :: Python :: 3.0
Classifier: Programming Language :: Python :: 3.1
Classifier: Programming Language :: Python :: 3.2
Classifier: Programming Language :: Python :: 3.3
Classifier: Programming Language :: Python :: 3.4
Classifier: Programming Language :: Python :: 3.5
Classifier: Programming Language :: Python :: 3.6
Classifier: Programming Language :: Python :: 3.7
Requires-Dist: requests (>=2.19.1)
